{
  "$schema": "https://schema.management.azure.com/schemas/2019-04-01/deploymentParameters.json#",
  "contentVersion": "1.0.0.0",
  "parameters": {
    "webAppName": {
      "value": "dotnetapp"
    },
    "hostingPlanName": {
      "value": "testing"
    },
    "appInsightsLocation": {
      "value": "eastus"
    },
    "sku": {
      "value": "F1"
    },
    "registryName": {
      "value": "saad4269"
    },
    "imageName": {
      "value": "ubuntu"
    },
    "registryLocation": {
      "value": "eastus"
    },
    "registrySku": {
      "value": "Standard_RAGRS"
    },
    "startupCommand": {
      "value": null
    }
  }
}
